{
  "commands": [
    {
      "name": "get_brightness",
      "request_type": "ioctl",
      "ioctl_code": 2153775104,
      "data_length": 4,
      "is_read": true
    },
    {
      "name": "set_brightness",
      "request_type": "ioctl",
      "ioctl_code": 2153775104,
      "data_length": 0,
      "is_read": false,
      "value": 150
    },
    {
      "name": "get_contrast",
      "request_type": "ioctl",
      "ioctl_code": 2153775105,
      "data_length": 4,
      "is_read": true
    },
    {
      "name": "set_contrast",
      "request_type": "ioctl",
      "ioctl_code": 2153775105,
      "data_length": 0,
      "is_read": false,
      "value": 50
    },
    {
      "name": "get_hue",
      "request_type": "ioctl",
      "ioctl_code": 2153775107,
      "data_length": 4,
      "is_read": true
    },
    {
      "name": "set_hue",
      "request_type": "ioctl",
      "ioctl_code": 2153775107,
      "data_length": 0,
      "is_read": false,
      "value": 0
    }
  ]
}
